<annotation>
	<folder>A</folder>
	<filename>A.d68f3918-bf7c-11eb-b6ae-3ca067262819.jpg</filename>
	<path>E:\STMIK TASIKMALAYA\Skripsi\sibi_detection\images\collectedimages\A\A.d68f3918-bf7c-11eb-b6ae-3ca067262819.jpg</path>
	<source>
		<database>Unknown</database>
	</source>
	<size>
		<width>640</width>
		<height>480</height>
		<depth>3</depth>
	</size>
	<segmented>0</segmented>
	<object>
		<name>A</name>
		<pose>Unspecified</pose>
		<truncated>0</truncated>
		<difficult>0</difficult>
		<bndbox>
			<xmin>431</xmin>
			<ymin>222</ymin>
			<xmax>497</xmax>
			<ymax>305</ymax>
		</bndbox>
	</object>
</annotation>
