<annotation>
	<folder>E</folder>
	<filename>E.2ce2c9a4-bea3-11eb-924a-88d7f6271fd3.jpg</filename>
	<path>E:\STMIK TASIKMALAYA\Skripsi\sibi_vokal\images\collectedimages\E\E.2ce2c9a4-bea3-11eb-924a-88d7f6271fd3.jpg</path>
	<source>
		<database>Unknown</database>
	</source>
	<size>
		<width>640</width>
		<height>480</height>
		<depth>3</depth>
	</size>
	<segmented>0</segmented>
	<object>
		<name>E</name>
		<pose>Unspecified</pose>
		<truncated>0</truncated>
		<difficult>0</difficult>
		<bndbox>
			<xmin>190</xmin>
			<ymin>244</ymin>
			<xmax>235</xmax>
			<ymax>294</ymax>
		</bndbox>
	</object>
</annotation>
