<annotation>
	<folder>E</folder>
	<filename>E.814de980-c682-11eb-b104-88d7f6271fd3.jpg</filename>
	<path>E:\STMIK TASIKMALAYA\Skripsi\sibi_vokal\images\collectedimages\E\E.814de980-c682-11eb-b104-88d7f6271fd3.jpg</path>
	<source>
		<database>Unknown</database>
	</source>
	<size>
		<width>640</width>
		<height>480</height>
		<depth>3</depth>
	</size>
	<segmented>0</segmented>
	<object>
		<name>E</name>
		<pose>Unspecified</pose>
		<truncated>0</truncated>
		<difficult>0</difficult>
		<bndbox>
			<xmin>431</xmin>
			<ymin>240</ymin>
			<xmax>481</xmax>
			<ymax>295</ymax>
		</bndbox>
	</object>
</annotation>
