<annotation>
	<folder>I</folder>
	<filename>I.37642124-c67e-11eb-a40b-88d7f6271fd3.jpg</filename>
	<path>E:\STMIK TASIKMALAYA\Skripsi\sibi_vokal\images\collectedimages\I\I.37642124-c67e-11eb-a40b-88d7f6271fd3.jpg</path>
	<source>
		<database>Unknown</database>
	</source>
	<size>
		<width>640</width>
		<height>480</height>
		<depth>3</depth>
	</size>
	<segmented>0</segmented>
	<object>
		<name>I</name>
		<pose>Unspecified</pose>
		<truncated>0</truncated>
		<difficult>0</difficult>
		<bndbox>
			<xmin>212</xmin>
			<ymin>220</ymin>
			<xmax>256</xmax>
			<ymax>284</ymax>
		</bndbox>
	</object>
</annotation>
